[
  {
    "name": "crypto_HMAC",
    "tags": [
      "crypto",
      "HMAC"
    ],
    "version": "local-version",
    "basename": "HMAC.js",
    "displayName": "HMAC",
    "basedir": "crypto",
    "filePath": "crypto/HMAC.shape",
    "image": "crypto/HMAC.png"
  },
  {
    "name": "crypto_SaltGenerator",
    "tags": [
      "crypto",
      "SaltGenerator"
    ],
    "version": "local-version",
    "basename": "SaltGenerator.js",
    "displayName": "SaltGenerator",
    "basedir": "crypto",
    "filePath": "crypto/SaltGenerator.shape",
    "image": "crypto/SaltGenerator.png"
  },
  {
    "name": "crypto_SHA256",
    "tags": [
      "crypto",
      "SHA256"
    ],
    "version": "local-version",
    "basename": "SHA256.js",
    "displayName": "SHA256",
    "basedir": "crypto",
    "filePath": "crypto/SHA256.shape",
    "image": "crypto/SHA256.png"
  },
  {
    "name": "db_add_key_value",
    "tags": [
      "db",
      "add",
      "key",
      "value"
    ],
    "version": "local-version",
    "basename": "add_key_value.js",
    "displayName": "add_key_value",
    "basedir": "db",
    "filePath": "db/add_key_value.shape",
    "image": "db/add_key_value.png"
  },
  {
    "name": "documentation_Markdown",
    "tags": [
      "documentation",
      "Markdown"
    ],
    "version": "local-version",
    "basename": "Markdown.js",
    "displayName": "Markdown",
    "basedir": "documentation",
    "filePath": "documentation/Markdown.shape",
    "image": "documentation/Markdown.png"
  },
  {
    "name": "documentation_Text",
    "tags": [
      "documentation",
      "Text"
    ],
    "version": "local-version",
    "basename": "Text.js",
    "displayName": "Text",
    "basedir": "documentation",
    "filePath": "documentation/Text.shape",
    "image": "documentation/Text.png"
  },
  {
    "name": "text_concatenate",
    "tags": [
      "text",
      "concatenate"
    ],
    "version": "local-version",
    "basename": "concatenate.js",
    "displayName": "concatenate",
    "basedir": "text",
    "filePath": "text/concatenate.shape",
    "image": "text/concatenate.png"
  },
  {
    "name": "text_display",
    "tags": [
      "text",
      "display"
    ],
    "version": "local-version",
    "basename": "display.js",
    "displayName": "display",
    "basedir": "text",
    "filePath": "text/display.shape",
    "image": "text/display.png"
  },
  {
    "name": "text_equal",
    "tags": [
      "text",
      "equal"
    ],
    "version": "local-version",
    "basename": "equal.js",
    "displayName": "equal",
    "basedir": "text",
    "filePath": "text/equal.shape",
    "image": "text/equal.png"
  },
  {
    "name": "text_input",
    "tags": [
      "text",
      "input"
    ],
    "version": "local-version",
    "basename": "input.js",
    "displayName": "input",
    "basedir": "text",
    "filePath": "text/input.shape",
    "image": "text/input.png"
  },
  {
    "name": "text_length",
    "tags": [
      "text",
      "length"
    ],
    "version": "local-version",
    "basename": "length.js",
    "displayName": "length",
    "basedir": "text",
    "filePath": "text/length.shape",
    "image": "text/length.png"
  },
  {
    "name": "text_split",
    "tags": [
      "text",
      "split"
    ],
    "version": "local-version",
    "basename": "split.js",
    "displayName": "split",
    "basedir": "text",
    "filePath": "text/split.shape",
    "image": "text/split.png"
  }
]